{
  "reqs": [
    {
      "group": 2,
      "time": 3,
      "req_id": 8,
      "req_id_list": [

      ],
      "begintime": 1,
      "outermost": true
    },
    {
      "group": 3,
      "time": 1,
      "req_id": 4,
      "req_id_list": [

      ],
      "begintime": 75,
      "outermost": true
    },
    {
      "group": 3,
      "time": 1,
      "req_id": 4,
      "req_id_list": [

      ],
      "begintime": 75,
      "outermost": true
    },
    {
      "group": 1,
      "time": 4,
      "req_id": 6,
      "req_id_list": [

      ],
      "begintime": 54,
      "outermost": true
    },
    {
      "group": 1,
      "time": 4,
      "req_id": 6,
      "req_id_list": [

      ],
      "begintime": 54,
      "outermost": true
    },
    {
      "group": 2,
      "time": 3,
      "req_id": 8,
      "req_id_list": [

      ],
      "begintime": 1,
      "outermost": true
    },
    {
      "group": 4,
      "time": 2,
      "req_id": 2,
      "req_id_list": [

      ],
      "begintime": 60,
      "outermost": true
    },
    {
      "group": 4,
      "time": 2,
      "req_id": 2,
      "req_id_list": [

      ],
      "begintime": 60,
      "outermost": true
    }
  ]
}
