{
  "tasks": [
    {
      "task_id": 10,
      "proc": 2,
      "period": 4569.89,
      "extime": 407.48,
      "priority": 8,
      "offset": 0.0,
      "req_id_list": [
        61,
        30,
        88
      ]
    },
    {
      "task_id": 11,
      "proc": 3,
      "period": 5558.89,
      "extime": 331.06,
      "priority": 8,
      "offset": 0.0,
      "req_id_list": [
        80,
        13
      ]
    },
    {
      "task_id": 14,
      "proc": 4,
      "period": 15689.23,
      "extime": 167.0,
      "priority": 9,
      "offset": 0.0,
      "req_id_list": [
        44,
        39
      ]
    },
    {
      "task_id": 9,
      "proc": 1,
      "period": 17530.71,
      "extime": 250.56,
      "priority": 10,
      "offset": 0.0,
      "req_id_list": [
        7
      ]
    },
    {
      "task_id": 4,
      "proc": 1,
      "period": 910.71,
      "extime": 94.34,
      "priority": 5,
      "offset": 0.0,
      "req_id_list": [
        13,
        83
      ]
    },
    {
      "task_id": 12,
      "proc": 1,
      "period": 1552.92,
      "extime": 122.76,
      "priority": 6,
      "offset": 0.0,
      "req_id_list": [
        62
      ]
    },
    {
      "task_id": 1,
      "proc": 1,
      "period": 2499.58,
      "extime": 217.0,
      "priority": 7,
      "offset": 0.0,
      "req_id_list": [
        41
      ]
    },
    {
      "task_id": 8,
      "proc": 1,
      "period": 4459.46,
      "extime": 419.61,
      "priority": 8,
      "offset": 0.0,
      "req_id_list": [
        27,
        77
      ]
    },
    {
      "task_id": 5,
      "proc": 1,
      "period": 9260.68,
      "extime": 228.0,
      "priority": 9,
      "offset": 0.0,
      "req_id_list": [
        86
      ]
    },
    {
      "task_id": 9,
      "proc": 1,
      "period": 17530.71,
      "extime": 250.56,
      "priority": 10,
      "offset": 0.0,
      "req_id_list": [
        7
      ]
    },
    {
      "task_id": 4,
      "proc": 1,
      "period": 910.71,
      "extime": 94.34,
      "priority": 5,
      "offset": 0.0,
      "req_id_list": [
        13,
        83
      ]
    },
    {
      "task_id": 16,
      "proc": 3,
      "period": 2773.53,
      "extime": 294.06,
      "priority": 7,
      "offset": 0.0,
      "req_id_list": [
        61,
        35,
        6
      ]
    },
    {
      "task_id": 19,
      "proc": 2,
      "period": 3535.1,
      "extime": 205.18,
      "priority": 7,
      "offset": 0.0,
      "req_id_list": [
        2,
        76,
        6
      ]
    },
    {
      "task_id": 2,
      "proc": 4,
      "period": 3846.25,
      "extime": 368.0,
      "priority": 7,
      "offset": 0.0,
      "req_id_list": [
        86
      ]
    },
    {
      "task_id": 18,
      "proc": 2,
      "period": 16264.36,
      "extime": 369.38,
      "priority": 10,
      "offset": 0.0,
      "req_id_list": [
        85,
        57,
        2
      ]
    },
    {
      "task_id": 20,
      "proc": 4,
      "period": 27535.7,
      "extime": 517.6,
      "priority": 10,
      "offset": 0.0,
      "req_id_list": [
        87,
        5,
        20
      ]
    },
    {
      "task_id": 19,
      "proc": 2,
      "period": 3535.1,
      "extime": 205.18,
      "priority": 7,
      "offset": 0.0,
      "req_id_list": [
        2,
        76,
        6
      ]
    },
    {
      "task_id": 10,
      "proc": 2,
      "period": 4569.89,
      "extime": 407.48,
      "priority": 8,
      "offset": 0.0,
      "req_id_list": [
        61,
        30,
        88
      ]
    },
    {
      "task_id": 13,
      "proc": 2,
      "period": 10555.73,
      "extime": 161.0,
      "priority": 9,
      "offset": 0.0,
      "req_id_list": [
        81
      ]
    },
    {
      "task_id": 18,
      "proc": 2,
      "period": 16264.36,
      "extime": 369.38,
      "priority": 10,
      "offset": 0.0,
      "req_id_list": [
        85,
        57,
        2
      ]
    },
    {
      "task_id": 3,
      "proc": 3,
      "period": 1985.28,
      "extime": 127.0,
      "priority": 6,
      "offset": 0.0,
      "req_id_list": [
        7,
        29
      ]
    },
    {
      "task_id": 1,
      "proc": 1,
      "period": 2499.58,
      "extime": 217.0,
      "priority": 7,
      "offset": 0.0,
      "req_id_list": [
        41
      ]
    },
    {
      "task_id": 15,
      "proc": 4,
      "period": 7195.81,
      "extime": 512.61,
      "priority": 8,
      "offset": 0.0,
      "req_id_list": [
        1,
        73,
        46
      ]
    },
    {
      "task_id": 7,
      "proc": 3,
      "period": 8262.01,
      "extime": 202.34,
      "priority": 9,
      "offset": 0.0,
      "req_id_list": [
        81,
        55,
        37
      ]
    },
    {
      "task_id": 6,
      "proc": 3,
      "period": 11558.3,
      "extime": 277.02,
      "priority": 10,
      "offset": 0.0,
      "req_id_list": [
        34,
        53
      ]
    },
    {
      "task_id": 3,
      "proc": 3,
      "period": 1985.28,
      "extime": 127.0,
      "priority": 6,
      "offset": 0.0,
      "req_id_list": [
        7,
        29
      ]
    },
    {
      "task_id": 16,
      "proc": 3,
      "period": 2773.53,
      "extime": 294.06,
      "priority": 7,
      "offset": 0.0,
      "req_id_list": [
        61,
        35,
        6
      ]
    },
    {
      "task_id": 11,
      "proc": 3,
      "period": 5558.89,
      "extime": 331.06,
      "priority": 8,
      "offset": 0.0,
      "req_id_list": [
        80,
        13
      ]
    },
    {
      "task_id": 7,
      "proc": 3,
      "period": 8262.01,
      "extime": 202.34,
      "priority": 9,
      "offset": 0.0,
      "req_id_list": [
        81,
        55,
        37
      ]
    },
    {
      "task_id": 6,
      "proc": 3,
      "period": 11558.3,
      "extime": 277.02,
      "priority": 10,
      "offset": 0.0,
      "req_id_list": [
        34,
        53
      ]
    },
    {
      "task_id": 12,
      "proc": 1,
      "period": 1552.92,
      "extime": 122.76,
      "priority": 6,
      "offset": 0.0,
      "req_id_list": [
        62
      ]
    },
    {
      "task_id": 17,
      "proc": 4,
      "period": 1765.95,
      "extime": 178.19,
      "priority": 6,
      "offset": 0.0,
      "req_id_list": [
        31,
        60,
        35
      ]
    },
    {
      "task_id": 8,
      "proc": 1,
      "period": 4459.46,
      "extime": 419.61,
      "priority": 8,
      "offset": 0.0,
      "req_id_list": [
        27,
        77
      ]
    },
    {
      "task_id": 5,
      "proc": 1,
      "period": 9260.68,
      "extime": 228.0,
      "priority": 9,
      "offset": 0.0,
      "req_id_list": [
        86
      ]
    },
    {
      "task_id": 13,
      "proc": 2,
      "period": 10555.73,
      "extime": 161.0,
      "priority": 9,
      "offset": 0.0,
      "req_id_list": [
        81
      ]
    },
    {
      "task_id": 17,
      "proc": 4,
      "period": 1765.95,
      "extime": 178.19,
      "priority": 6,
      "offset": 0.0,
      "req_id_list": [
        31,
        60,
        35
      ]
    },
    {
      "task_id": 2,
      "proc": 4,
      "period": 3846.25,
      "extime": 368.0,
      "priority": 7,
      "offset": 0.0,
      "req_id_list": [
        86
      ]
    },
    {
      "task_id": 15,
      "proc": 4,
      "period": 7195.81,
      "extime": 512.61,
      "priority": 8,
      "offset": 0.0,
      "req_id_list": [
        1,
        73,
        46
      ]
    },
    {
      "task_id": 14,
      "proc": 4,
      "period": 15689.23,
      "extime": 167.0,
      "priority": 9,
      "offset": 0.0,
      "req_id_list": [
        44,
        39
      ]
    },
    {
      "task_id": 20,
      "proc": 4,
      "period": 27535.7,
      "extime": 517.6,
      "priority": 10,
      "offset": 0.0,
      "req_id_list": [
        87,
        5,
        20
      ]
    }
  ]
}