{
  "reqs": [
    {
      "req_id": 2,
      "group": 2,
      "time": 5.426171350700199,
      "req_id_list": [

      ],
      "begintime": 0,
      "outermost": true
    },
    {
      "req_id": 60,
      "group": 30,
      "time": 5.321274904366516,
      "req_id_list": [

      ],
      "begintime": 0,
      "outermost": true
    },
    {
      "req_id": 16,
      "group": 16,
      "time": 4.411906407459118,
      "req_id_list": [
        122
      ],
      "begintime": 0,
      "outermost": true
    },
    {
      "req_id": 122,
      "group": 18,
      "time": 1.4706354691530394,
      "req_id_list": [

      ],
      "begintime": 0,
      "outermost": true
    },
    {
      "req_id": 37,
      "group": 7,
      "time": 4.41185686941916,
      "req_id_list": [

      ],
      "begintime": 0,
      "outermost": true
    },
    {
      "req_id": 69,
      "group": 9,
      "time": 5.338025044027279,
      "req_id_list": [
        101
      ],
      "begintime": 0,
      "outermost": true
    },
    {
      "req_id": 101,
      "group": 23,
      "time": 1.7793416813424263,
      "req_id_list": [

      ],
      "begintime": 0,
      "outermost": true
    },
    {
      "req_id": 51,
      "group": 21,
      "time": 2.3635257370233753,
      "req_id_list": [

      ],
      "begintime": 0,
      "outermost": true
    },
    {
      "req_id": 25,
      "group": 25,
      "time": 4.34926108588325,
      "req_id_list": [

      ],
      "begintime": 0,
      "outermost": true
    },
    {
      "req_id": 82,
      "group": 22,
      "time": 2.44457451996746,
      "req_id_list": [

      ],
      "begintime": 0,
      "outermost": true
    },
    {
      "req_id": 25,
      "group": 25,
      "time": 4.34926108588325,
      "req_id_list": [

      ],
      "begintime": 0,
      "outermost": true
    },
    {
      "req_id": 94,
      "group": 32,
      "time": 27,
      "req_id_list": [

      ],
      "begintime": 0,
      "outermost": true
    },
    {
      "req_id": 53,
      "group": 23,
      "time": 1.4542471527222307,
      "req_id_list": [
        106,
        107
      ],
      "begintime": 0,
      "outermost": true
    },
    {
      "req_id": 106,
      "group": 4,
      "time": 0.4847490509074102,
      "req_id_list": [

      ],
      "begintime": 0,
      "outermost": true
    },
    {
      "req_id": 107,
      "group": 10,
      "time": 0.4847490509074102,
      "req_id_list": [

      ],
      "begintime": 0,
      "outermost": true
    },
    {
      "req_id": 9,
      "group": 9,
      "time": 3.3305242344154924,
      "req_id_list": [
        108,
        109
      ],
      "begintime": 0,
      "outermost": true
    },
    {
      "req_id": 108,
      "group": 28,
      "time": 1.1101747448051642,
      "req_id_list": [

      ],
      "begintime": 0,
      "outermost": true
    },
    {
      "req_id": 109,
      "group": 28,
      "time": 1.1101747448051642,
      "req_id_list": [

      ],
      "begintime": 0,
      "outermost": true
    },
    {
      "req_id": 85,
      "group": 25,
      "time": 6.38197790658576,
      "req_id_list": [
        110
      ],
      "begintime": 0,
      "outermost": true
    },
    {
      "req_id": 110,
      "group": 20,
      "time": 2.12732596886192,
      "req_id_list": [

      ],
      "begintime": 0,
      "outermost": true
    },
    {
      "req_id": 72,
      "group": 12,
      "time": 6.335670301352945,
      "req_id_list": [

      ],
      "begintime": 0,
      "outermost": true
    },
    {
      "req_id": 51,
      "group": 21,
      "time": 2.3635257370233753,
      "req_id_list": [

      ],
      "begintime": 0,
      "outermost": true
    },
    {
      "req_id": 30,
      "group": 30,
      "time": 3.473045189552238,
      "req_id_list": [

      ],
      "begintime": 0,
      "outermost": true
    },
    {
      "req_id": 27,
      "group": 27,
      "time": 3.4588342605804034,
      "req_id_list": [

      ],
      "begintime": 0,
      "outermost": true
    },
    {
      "req_id": 81,
      "group": 21,
      "time": 4.308420208169407,
      "req_id_list": [

      ],
      "begintime": 0,
      "outermost": true
    },
    {
      "req_id": 12,
      "group": 12,
      "time": 2.467275528870387,
      "req_id_list": [
        111,
        112
      ],
      "begintime": 0,
      "outermost": true
    },
    {
      "req_id": 111,
      "group": 13,
      "time": 0.822425176290129,
      "req_id_list": [

      ],
      "begintime": 0,
      "outermost": true
    },
    {
      "req_id": 112,
      "group": 16,
      "time": 0.822425176290129,
      "req_id_list": [

      ],
      "begintime": 0,
      "outermost": true
    },
    {
      "req_id": 79,
      "group": 19,
      "time": 6.483783811975044,
      "req_id_list": [

      ],
      "begintime": 0,
      "outermost": true
    },
    {
      "req_id": 94,
      "group": 32,
      "time": 27,
      "req_id_list": [

      ],
      "begintime": 0,
      "outermost": true
    },
    {
      "req_id": 65,
      "group": 5,
      "time": 6.361936358019496,
      "req_id_list": [
        113
      ],
      "begintime": 0,
      "outermost": true
    },
    {
      "req_id": 113,
      "group": 14,
      "time": 2.1206454526731653,
      "req_id_list": [

      ],
      "begintime": 0,
      "outermost": true
    },
    {
      "req_id": 14,
      "group": 14,
      "time": 1.4323696620795432,
      "req_id_list": [

      ],
      "begintime": 0,
      "outermost": true
    },
    {
      "req_id": 1,
      "group": 1,
      "time": 4.464951575375466,
      "req_id_list": [
        114,
        115
      ],
      "begintime": 0,
      "outermost": true
    },
    {
      "req_id": 114,
      "group": 5,
      "time": 1.4883171917918219,
      "req_id_list": [

      ],
      "begintime": 0,
      "outermost": true
    },
    {
      "req_id": 115,
      "group": 25,
      "time": 1.4883171917918219,
      "req_id_list": [

      ],
      "begintime": 0,
      "outermost": true
    },
    {
      "req_id": 45,
      "group": 15,
      "time": 4.316898342237433,
      "req_id_list": [

      ],
      "begintime": 0,
      "outermost": true
    },
    {
      "req_id": 79,
      "group": 19,
      "time": 6.483783811975044,
      "req_id_list": [

      ],
      "begintime": 0,
      "outermost": true
    },
    {
      "req_id": 49,
      "group": 19,
      "time": 2.3977672806291546,
      "req_id_list": [

      ],
      "begintime": 0,
      "outermost": true
    },
    {
      "req_id": 33,
      "group": 3,
      "time": 2.4318041728059065,
      "req_id_list": [
        116
      ],
      "begintime": 0,
      "outermost": true
    },
    {
      "req_id": 116,
      "group": 23,
      "time": 0.8106013909353021,
      "req_id_list": [

      ],
      "begintime": 0,
      "outermost": true
    },
    {
      "req_id": 41,
      "group": 11,
      "time": 6.4655670092125055,
      "req_id_list": [

      ],
      "begintime": 0,
      "outermost": true
    },
    {
      "req_id": 29,
      "group": 29,
      "time": 3.3785457172017415,
      "req_id_list": [
        117,
        118
      ],
      "begintime": 0,
      "outermost": true
    },
    {
      "req_id": 117,
      "group": 19,
      "time": 1.1261819057339137,
      "req_id_list": [

      ],
      "begintime": 0,
      "outermost": true
    },
    {
      "req_id": 118,
      "group": 21,
      "time": 1.1261819057339137,
      "req_id_list": [

      ],
      "begintime": 0,
      "outermost": true
    },
    {
      "req_id": 32,
      "group": 2,
      "time": 2.3686355223864144,
      "req_id_list": [
        119,
        120
      ],
      "begintime": 0,
      "outermost": true
    },
    {
      "req_id": 119,
      "group": 10,
      "time": 0.7895451741288048,
      "req_id_list": [

      ],
      "begintime": 0,
      "outermost": true
    },
    {
      "req_id": 120,
      "group": 21,
      "time": 0.7895451741288048,
      "req_id_list": [

      ],
      "begintime": 0,
      "outermost": true
    },
    {
      "req_id": 73,
      "group": 13,
      "time": 4.406216043941564,
      "req_id_list": [

      ],
      "begintime": 0,
      "outermost": true
    },
    {
      "req_id": 23,
      "group": 23,
      "time": 3.4423569290266722,
      "req_id_list": [
        121
      ],
      "begintime": 0,
      "outermost": true
    },
    {
      "req_id": 121,
      "group": 5,
      "time": 1.1474523096755573,
      "req_id_list": [

      ],
      "begintime": 0,
      "outermost": true
    },
    {
      "req_id": 18,
      "group": 18,
      "time": 3.400025265418139,
      "req_id_list": [

      ],
      "begintime": 0,
      "outermost": true
    },
    {
      "req_id": 16,
      "group": 16,
      "time": 4.411906407459118,
      "req_id_list": [
        122
      ],
      "begintime": 0,
      "outermost": true
    },
    {
      "req_id": 122,
      "group": 18,
      "time": 1.4706354691530394,
      "req_id_list": [

      ],
      "begintime": 0,
      "outermost": true
    },
    {
      "req_id": 64,
      "group": 4,
      "time": 4.438415131010414,
      "req_id_list": [
        123,
        124
      ],
      "begintime": 0,
      "outermost": true
    },
    {
      "req_id": 123,
      "group": 8,
      "time": 1.4794717103368047,
      "req_id_list": [

      ],
      "begintime": 0,
      "outermost": true
    },
    {
      "req_id": 124,
      "group": 1,
      "time": 1.4794717103368047,
      "req_id_list": [

      ],
      "begintime": 0,
      "outermost": true
    },
    {
      "req_id": 15,
      "group": 15,
      "time": 4.491662503109247,
      "req_id_list": [

      ],
      "begintime": 0,
      "outermost": true
    },
    {
      "req_id": 43,
      "group": 13,
      "time": 5.419512957684201,
      "req_id_list": [
        125,
        126
      ],
      "begintime": 0,
      "outermost": true
    },
    {
      "req_id": 125,
      "group": 8,
      "time": 1.8065043192280672,
      "req_id_list": [

      ],
      "begintime": 0,
      "outermost": true
    },
    {
      "req_id": 126,
      "group": 12,
      "time": 1.8065043192280672,
      "req_id_list": [

      ],
      "begintime": 0,
      "outermost": true
    },
    {
      "req_id": 24,
      "group": 24,
      "time": 2.345890770270307,
      "req_id_list": [
        127
      ],
      "begintime": 0,
      "outermost": true
    },
    {
      "req_id": 127,
      "group": 11,
      "time": 0.7819635900901023,
      "req_id_list": [

      ],
      "begintime": 0,
      "outermost": true
    }
  ]
}